Metadata-Version: 2.1
Name: pywitness
Version: 0.0.1
Summary: A package for monitoring and parsing (log) files generated by launched or watched processes
Home-page: https://gitlab.com/Jaap.vanderVelde/pywitness
Author: BMT, Jaap van der Velde
Author-email: jaap.vandervelde@bmtglobal.com
License: MIT
Download-URL: https://gitlab.com/Jaap.vanderVelde/pywitness/repository/archive.zip?ref=0.0.1
Keywords: package,download,monitoring,logging,CLI,client
Platform: UNKNOWN
Classifier: Development Status :: 2 - Pre-Alpha
Classifier: Intended Audience :: Developers
Classifier: Topic :: System :: Distributed Computing
Classifier: License :: OSI Approved :: MIT License
Classifier: Programming Language :: Python :: 3.9
Requires-Python: >=3.9
